[{"name":"마력포_테스트마력포_01","level":60,"grade":"영웅","type":"무기","subType":"마력포","code":"101900000","trade":false,"enchantLevel":0},{"name":"마력포_테스트마력포_02","level":60,"grade":"영웅","type":"무기","subType":"마력포","code":"101900007","trade":false,"enchantLevel":0},{"name":"달인의 빛나는 아다만티움 마력포","level":35,"grade":"유일","type":"무기","subType":"마력포","code":"101900019","trade":false,"enchantLevel":0},{"name":"달인의 빛나는 강화 아다만티움 마력포","level":40,"grade":"유일","type":"무기","subType":"마력포","code":"101900020","trade":false,"enchantLevel":0},{"name":"달인의 빛나는 아다만티움 마력포","level":35,"grade":"유일","type":"무기","subType":"마력포","code":"101900031","trade":false,"enchantLevel":0},{"name":"달인의 빛나는 강화 아다만티움 마력포","level":40,"grade":"유일","type":"무기","subType":"마력포","code":"101900032","trade":false,"enchantLevel":0},{"name":"달인의 빛나는 오리하르콘 마력포","level":45,"grade":"유일","type":"무기","subType":"마력포","code":"101900037","trade":false,"enchantLevel":0},{"name":"달인의 빛나는 강화 오리하르콘 마력포","level":50,"grade":"유일","type":"무기","subType":"마력포","code":"101900038","trade":false,"enchantLevel":0},{"name":"달인의 빛나는 오리하르콘 마력포","level":45,"grade":"유일","type":"무기","subType":"마력포","code":"101900043","trade":false,"enchantLevel":0},{"name":"달인의 빛나는 강화 오리하르콘 마력포","level":50,"grade":"유일","type":"무기","subType":"마력포","code":"101900044","trade":false,"enchantLevel":0},{"name":"빛나는 백룡왕의 마력포","level":40,"grade":"유일","type":"무기","subType":"마력포","code":"101900047","trade":false,"enchantLevel":0},{"name":"빛나는 명룡왕의 마력포","level":50,"grade":"유일","type":"무기","subType":"마력포","code":"101900049","trade":false,"enchantLevel":0},{"name":"빛나는 흑룡왕의 마력포","level":40,"grade":"유일","type":"무기","subType":"마력포","code":"101900052","trade":false,"enchantLevel":0},{"name":"빛나는 암룡왕의 마력포","level":50,"grade":"유일","type":"무기","subType":"마력포","code":"101900054","trade":false,"enchantLevel":0},{"name":"풍림 화산의 마력포","level":44,"grade":"유일","type":"무기","subType":"마력포","code":"101900068","trade":false,"enchantLevel":0},{"name":"풍림 화산의 마력포","level":44,"grade":"유일","type":"무기","subType":"마력포","code":"101900069","trade":false,"enchantLevel":0},{"name":"드라즈마의 마력포","level":50,"grade":"유일","type":"무기","subType":"마력포","code":"101900070","trade":false,"enchantLevel":0},{"name":"드라즈마의 마력포","level":50,"grade":"유일","type":"무기","subType":"마력포","code":"101900071","trade":false,"enchantLevel":0},{"name":"달인의 빛나는 드레니움 마력포","level":55,"grade":"유일","type":"무기","subType":"마력포","code":"101900074","trade":false,"enchantLevel":0},{"name":"명인의 빛나는 드레니움 마력포","level":55,"grade":"영웅","type":"무기","subType":"마력포","code":"101900075","trade":false,"enchantLevel":0},{"name":"달인의 빛나는 드레니움 마력포","level":55,"grade":"유일","type":"무기","subType":"마력포","code":"101900078","trade":false,"enchantLevel":0},{"name":"명인의 빛나는 드레니움 마력포","level":55,"grade":"영웅","type":"무기","subType":"마력포","code":"101900079","trade":false,"enchantLevel":0},{"name":"빛나는 응룡왕의 마력포","level":55,"grade":"유일","type":"무기","subType":"마력포","code":"101900081","trade":false,"enchantLevel":0},{"name":"빛나는 응룡 천황의 마력포","level":55,"grade":"영웅","type":"무기","subType":"마력포","code":"101900082","trade":false,"enchantLevel":0},{"name":"빛나는 기룡왕의 마력포","level":55,"grade":"유일","type":"무기","subType":"마력포","code":"101900084","trade":false,"enchantLevel":0},{"name":"빛나는 기룡 천황의 마력포","level":55,"grade":"영웅","type":"무기","subType":"마력포","code":"101900085","trade":false,"enchantLevel":0},{"name":"타흐의 마력포","level":52,"grade":"유일","type":"무기","subType":"마력포","code":"101900086","trade":false,"enchantLevel":0},{"name":"묘지기 바사임의 마력포","level":52,"grade":"유일","type":"무기","subType":"마력포","code":"101900087","trade":false,"enchantLevel":0},{"name":"달인의 빛나는 강화 드레니움 마력포","level":58,"grade":"유일","type":"무기","subType":"마력포","code":"101900090","trade":false,"enchantLevel":0},{"name":"명인의 빛나는 강화 드레니움 마력포","level":58,"grade":"영웅","type":"무기","subType":"마력포","code":"101900091","trade":false,"enchantLevel":0},{"name":"달인의 빛나는 강화 드레니움 마력포","level":58,"grade":"유일","type":"무기","subType":"마력포","code":"101900094","trade":false,"enchantLevel":0},{"name":"명인의 빛나는 강화 드레니움 마력포","level":58,"grade":"영웅","type":"무기","subType":"마력포","code":"101900095","trade":false,"enchantLevel":0},{"name":"빛나는 응룡왕의 강화 마력포","level":60,"grade":"유일","type":"무기","subType":"마력포","code":"101900097","trade":false,"enchantLevel":0},{"name":"빛나는 응룡 천황의 강화 마력포","level":60,"grade":"영웅","type":"무기","subType":"마력포","code":"101900098","trade":false,"enchantLevel":0},{"name":"빛나는 기룡왕의 강화 마력포","level":60,"grade":"유일","type":"무기","subType":"마력포","code":"101900100","trade":false,"enchantLevel":0},{"name":"빛나는 기룡 천황의 강화 마력포","level":60,"grade":"영웅","type":"무기","subType":"마력포","code":"101900101","trade":false,"enchantLevel":0},{"name":"빛나는 풍림 화산의 마력포","level":44,"grade":"유일","type":"무기","subType":"마력포","code":"101900161","trade":false,"enchantLevel":0},{"name":"빛나는 풍림 화산의 마력포","level":44,"grade":"유일","type":"무기","subType":"마력포","code":"101900162","trade":false,"enchantLevel":0},{"name":"빛나는 드라즈마의 마력포","level":50,"grade":"유일","type":"무기","subType":"마력포","code":"101900163","trade":false,"enchantLevel":0},{"name":"빛나는 드라즈마의 마력포","level":50,"grade":"유일","type":"무기","subType":"마력포","code":"101900164","trade":false,"enchantLevel":0},{"name":"명인의 드레니움 마력포","level":55,"grade":"유일","type":"무기","subType":"마력포","code":"101900168","trade":false,"enchantLevel":0},{"name":"명인의 드레니움 마력포","level":55,"grade":"유일","type":"무기","subType":"마력포","code":"101900172","trade":false,"enchantLevel":0},{"name":"응룡 천황의 마력포","level":55,"grade":"유일","type":"무기","subType":"마력포","code":"101900175","trade":false,"enchantLevel":0},{"name":"기룡 천황의 마력포","level":55,"grade":"유일","type":"무기","subType":"마력포","code":"101900178","trade":false,"enchantLevel":0},{"name":"빛나는 타흐의 마력포","level":52,"grade":"유일","type":"무기","subType":"마력포","code":"101900179","trade":false,"enchantLevel":0},{"name":"빛나는 묘지기 바사임의 마력포","level":52,"grade":"유일","type":"무기","subType":"마력포","code":"101900180","trade":false,"enchantLevel":0},{"name":"명인의 강화 드레니움 마력포","level":58,"grade":"유일","type":"무기","subType":"마력포","code":"101900184","trade":false,"enchantLevel":0},{"name":"고결한 명인의 강화 드레니움 마력포","level":60,"grade":"영웅","type":"무기","subType":"마력포","code":"101900185","trade":false,"enchantLevel":0},{"name":"명인의 강화 드레니움 마력포","level":58,"grade":"유일","type":"무기","subType":"마력포","code":"101900189","trade":false,"enchantLevel":0},{"name":"고결한 명인의 강화 드레니움 마력포","level":60,"grade":"영웅","type":"무기","subType":"마력포","code":"101900190","trade":false,"enchantLevel":0},{"name":"응룡 천황의 강화 마력포","level":60,"grade":"유일","type":"무기","subType":"마력포","code":"101900193","trade":false,"enchantLevel":0},{"name":"기룡 천황의 강화 마력포","level":60,"grade":"유일","type":"무기","subType":"마력포","code":"101900196","trade":false,"enchantLevel":0},{"name":"하늘의 마력포","level":25,"grade":"유일","type":"무기","subType":"마력포","code":"101900266","trade":false,"enchantLevel":0},{"name":"심판의 마력포","level":35,"grade":"유일","type":"무기","subType":"마력포","code":"101900271","trade":false,"enchantLevel":0},{"name":"혼돈의 마력포","level":35,"grade":"유일","type":"무기","subType":"마력포","code":"101900272","trade":false,"enchantLevel":0},{"name":"살기타격","level":25,"grade":"유일","type":"무기","subType":"마력포","code":"101900282","trade":false,"enchantLevel":0},{"name":"사탄의 마력포","level":35,"grade":"유일","type":"무기","subType":"마력포","code":"101900289","trade":false,"enchantLevel":0},{"name":"크로메데의 마력포","level":35,"grade":"유일","type":"무기","subType":"마력포","code":"101900290","trade":false,"enchantLevel":0},{"name":"무하카카의 마력포","level":40,"grade":"유일","type":"무기","subType":"마력포","code":"101900294","trade":false,"enchantLevel":0},{"name":"천사장의 마력포","level":30,"grade":"유일","type":"무기","subType":"마력포","code":"101900311","trade":false,"enchantLevel":0},{"name":"사신의 마력포","level":40,"grade":"유일","type":"무기","subType":"마력포","code":"101900312","trade":false,"enchantLevel":0},{"name":"몰락한 고대신의 마력포","level":50,"grade":"유일","type":"무기","subType":"마력포","code":"101900313","trade":false,"enchantLevel":0},{"name":"파천포","level":41,"grade":"유일","type":"무기","subType":"마력포","code":"101900317","trade":false,"enchantLevel":0},{"name":"메노티오스의 마력포","level":50,"grade":"유일","type":"무기","subType":"마력포","code":"101900318","trade":false,"enchantLevel":0},{"name":"알루키나의 마력포","level":44,"grade":"유일","type":"무기","subType":"마력포","code":"101900436","trade":false,"enchantLevel":0},{"name":"어두운 황혼의 마력포","level":50,"grade":"유일","type":"무기","subType":"마력포","code":"101900439","trade":false,"enchantLevel":0},{"name":"절명포","level":46,"grade":"유일","type":"무기","subType":"마력포","code":"101900478","trade":false,"enchantLevel":0},{"name":"자피엘의 마력포","level":48,"grade":"유일","type":"무기","subType":"마력포","code":"101900481","trade":false,"enchantLevel":0},{"name":"검은 심장의 마력포","level":50,"grade":"유일","type":"무기","subType":"마력포","code":"101900483","trade":false,"enchantLevel":0},{"name":"은총의 마력포","level":45,"grade":"유일","type":"무기","subType":"마력포","code":"101900484","trade":false,"enchantLevel":0},{"name":"파멸의 마력포","level":45,"grade":"유일","type":"무기","subType":"마력포","code":"101900485","trade":false,"enchantLevel":0},{"name":"가디언 천부장의 마력포","level":50,"grade":"유일","type":"무기","subType":"마력포","code":"101900490","trade":false,"enchantLevel":0},{"name":"아칸 천부장의 마력포","level":50,"grade":"유일","type":"무기","subType":"마력포","code":"101900491","trade":false,"enchantLevel":0},{"name":"베토니의 마력포","level":45,"grade":"유일","type":"무기","subType":"마력포","code":"101900500","trade":false,"enchantLevel":0},{"name":"크세노폰의 마력포","level":45,"grade":"유일","type":"무기","subType":"마력포","code":"101900511","trade":false,"enchantLevel":0},{"name":"용신장의 마력포","level":50,"grade":"유일","type":"무기","subType":"마력포","code":"101900516","trade":false,"enchantLevel":0},{"name":"백염의 마력포","level":35,"grade":"유일","type":"무기","subType":"마력포","code":"101900522","trade":false,"enchantLevel":0},{"name":"가디언 십부장의 마력포","level":30,"grade":"유일","type":"무기","subType":"마력포","code":"101900545","trade":false,"enchantLevel":0},{"name":"가디언 백부장의 마력포","level":40,"grade":"유일","type":"무기","subType":"마력포","code":"101900546","trade":false,"enchantLevel":0},{"name":"아칸 십부장의 마력포","level":30,"grade":"유일","type":"무기","subType":"마력포","code":"101900547","trade":false,"enchantLevel":0},{"name":"아칸 백부장의 마력포","level":40,"grade":"유일","type":"무기","subType":"마력포","code":"101900548","trade":false,"enchantLevel":0},{"name":"미라젠트의 마력포","level":50,"grade":"유일","type":"무기","subType":"마력포","code":"101900553","trade":false,"enchantLevel":0},{"name":"펜릴의 마력포","level":50,"grade":"유일","type":"무기","subType":"마력포","code":"101900554","trade":false,"enchantLevel":0},{"name":"천군 3급 정예 군단병의 마력포","level":46,"grade":"유일","type":"무기","subType":"마력포","code":"101900559","trade":false,"enchantLevel":0},{"name":"마군 3급 정예 군단병의 마력포","level":46,"grade":"유일","type":"무기","subType":"마력포","code":"101900561","trade":false,"enchantLevel":0},{"name":"트리로언의 마력포","level":50,"grade":"유일","type":"무기","subType":"마력포","code":"101900564","trade":false,"enchantLevel":0},{"name":"란마르크의 마력포","level":50,"grade":"유일","type":"무기","subType":"마력포","code":"101900565","trade":false,"enchantLevel":0},{"name":"아누하르트 정예병의 마력포","level":50,"grade":"유일","type":"무기","subType":"마력포","code":"101900570","trade":false,"enchantLevel":0},{"name":"타하바타의 마력포","level":50,"grade":"영웅","type":"무기","subType":"마력포","code":"101900571","trade":false,"enchantLevel":0},{"name":"신룡포","level":48,"grade":"유일","type":"무기","subType":"마력포","code":"101900572","trade":false,"enchantLevel":0},{"name":"신룡포","level":48,"grade":"유일","type":"무기","subType":"마력포","code":"101900573","trade":false,"enchantLevel":0},{"name":"후트킨의 마력포","level":44,"grade":"유일","type":"무기","subType":"마력포","code":"101900574","trade":false,"enchantLevel":0},{"name":"임시 데이터 마력포","level":35,"grade":"유일","type":"무기","subType":"마력포","code":"101900580","trade":false,"enchantLevel":0},{"name":"임시 데이터 마력포","level":45,"grade":"유일","type":"무기","subType":"마력포","code":"101900581","trade":false,"enchantLevel":0},{"name":"정예 가디언 천부장의 마력포","level":50,"grade":"유일","type":"무기","subType":"마력포","code":"101900582","trade":false,"enchantLevel":0},{"name":"임시 데이터 마력포","level":35,"grade":"유일","type":"무기","subType":"마력포","code":"101900583","trade":false,"enchantLevel":0},{"name":"임시 데이터 마력포","level":45,"grade":"유일","type":"무기","subType":"마력포","code":"101900584","trade":false,"enchantLevel":0},{"name":"정예 아칸 천부장의 마력포","level":50,"grade":"유일","type":"무기","subType":"마력포","code":"101900585","trade":false,"enchantLevel":0},{"name":"정예 가디언 십부장의 마력포","level":30,"grade":"유일","type":"무기","subType":"마력포","code":"101900589","trade":false,"enchantLevel":0},{"name":"정예 가디언 백부장의 마력포","level":40,"grade":"유일","type":"무기","subType":"마력포","code":"101900590","trade":false,"enchantLevel":0},{"name":"정예 아칸 십부장의 마력포","level":30,"grade":"유일","type":"무기","subType":"마력포","code":"101900591","trade":false,"enchantLevel":0},{"name":"정예 아칸 백부장의 마력포","level":40,"grade":"유일","type":"무기","subType":"마력포","code":"101900592","trade":false,"enchantLevel":0},{"name":"제47 군단장의 마력포","level":50,"grade":"유일","type":"무기","subType":"마력포","code":"101900593","trade":false,"enchantLevel":0},{"name":"평정의 마력포","level":55,"grade":"유일","type":"무기","subType":"마력포","code":"101900605","trade":false,"enchantLevel":0},{"name":"55레벨 마족 랜덤 드롭 U1 마력포","level":55,"grade":"유일","type":"무기","subType":"마력포","code":"101900615","trade":false,"enchantLevel":0},{"name":"드빌카림의 마력포","level":52,"grade":"유일","type":"무기","subType":"마력포","code":"101900625","trade":false,"enchantLevel":0},{"name":"검은 폭풍의 마력포","level":55,"grade":"유일","type":"무기","subType":"마력포","code":"101900626","trade":false,"enchantLevel":0},{"name":"루드라의 마력포","level":55,"grade":"영웅","type":"무기","subType":"마력포","code":"101900627","trade":false,"enchantLevel":0},{"name":"세마타의 마력포","level":55,"grade":"영웅","type":"무기","subType":"마력포","code":"101900633","trade":false,"enchantLevel":0},{"name":"분노한 헤라나스의 마력포","level":55,"grade":"영웅","type":"무기","subType":"마력포","code":"101900634","trade":false,"enchantLevel":0},{"name":"파드마샤의 마력포","level":55,"grade":"영웅","type":"무기","subType":"마력포","code":"101900638","trade":false,"enchantLevel":0},{"name":"분노한 테그라크의 마력포","level":55,"grade":"영웅","type":"무기","subType":"마력포","code":"101900639","trade":false,"enchantLevel":0},{"name":"가디언 만부장의 마력포","level":55,"grade":"유일","type":"무기","subType":"마력포","code":"101900642","trade":false,"enchantLevel":0},{"name":"가디언 군단장의 마력포","level":55,"grade":"영웅","type":"무기","subType":"마력포","code":"101900643","trade":false,"enchantLevel":0},{"name":"아칸 만부장의 마력포","level":55,"grade":"유일","type":"무기","subType":"마력포","code":"101900646","trade":false,"enchantLevel":0},{"name":"아칸 군단장의 마력포","level":55,"grade":"영웅","type":"무기","subType":"마력포","code":"101900647","trade":false,"enchantLevel":0},{"name":"천군 2급 정예 군단병의 마력포","level":51,"grade":"유일","type":"무기","subType":"마력포","code":"101900648","trade":false,"enchantLevel":0},{"name":"마군 2급 정예 군단병의 마력포","level":51,"grade":"유일","type":"무기","subType":"마력포","code":"101900649","trade":false,"enchantLevel":0},{"name":"라이스트리고스의 마력포","level":54,"grade":"유일","type":"무기","subType":"마력포","code":"101900651","trade":false,"enchantLevel":0},{"name":"환영의 라이스트리고스의 마력포","level":54,"grade":"유일","type":"무기","subType":"마력포","code":"101900652","trade":false,"enchantLevel":0},{"name":"시엘의 권능 마력포","level":55,"grade":"유일","type":"무기","subType":"마력포","code":"101900653","trade":false,"enchantLevel":0},{"name":"카이시넬의 은총 마력포","level":55,"grade":"영웅","type":"무기","subType":"마력포","code":"101900654","trade":false,"enchantLevel":0},{"name":"베르드폴니르의 마력포","level":54,"grade":"유일","type":"무기","subType":"마력포","code":"101900656","trade":false,"enchantLevel":0},{"name":"운명의 베르드폴니르의 마력포","level":54,"grade":"유일","type":"무기","subType":"마력포","code":"101900657","trade":false,"enchantLevel":0},{"name":"시엘의 권능 마력포","level":55,"grade":"유일","type":"무기","subType":"마력포","code":"101900658","trade":false,"enchantLevel":0},{"name":"마르쿠탄의 은총 마력포","level":55,"grade":"영웅","type":"무기","subType":"마력포","code":"101900659","trade":false,"enchantLevel":0},{"name":"숙련된 사냥꾼의 마력포","level":53,"grade":"유일","type":"무기","subType":"마력포","code":"101900665","trade":false,"enchantLevel":0},{"name":"숙련된 조사원의 마력포","level":53,"grade":"유일","type":"무기","subType":"마력포","code":"101900667","trade":false,"enchantLevel":0},{"name":"수비대장의 마력포","level":54,"grade":"유일","type":"무기","subType":"마력포","code":"101900669","trade":false,"enchantLevel":0},{"name":"천군 5급 정예 군단병의 마력포","level":36,"grade":"유일","type":"무기","subType":"마력포","code":"101900685","trade":false,"enchantLevel":0},{"name":"천군 4급 정예 군단병의 마력포","level":41,"grade":"유일","type":"무기","subType":"마력포","code":"101900686","trade":false,"enchantLevel":0},{"name":"마군 5급 정예 군단병의 마력포","level":36,"grade":"유일","type":"무기","subType":"마력포","code":"101900701","trade":false,"enchantLevel":0},{"name":"마군 4급 정예 군단병의 마력포","level":41,"grade":"유일","type":"무기","subType":"마력포","code":"101900702","trade":false,"enchantLevel":0},{"name":"잊혀진 심연의 마력포","level":52,"grade":"유일","type":"무기","subType":"마력포","code":"101900706","trade":false,"enchantLevel":0},{"name":"야멘네스의 마력포","level":55,"grade":"영웅","type":"무기","subType":"마력포","code":"101900707","trade":false,"enchantLevel":0},{"name":"칼리가의 마력포","level":38,"grade":"유일","type":"무기","subType":"마력포","code":"101900708","trade":false,"enchantLevel":0},{"name":"천군 3급 정예 군단병의 마력포","level":46,"grade":"유일","type":"무기","subType":"마력포","code":"101900709","trade":false,"enchantLevel":0},{"name":"마군 3급 정예 군단병의 마력포","level":46,"grade":"유일","type":"무기","subType":"마력포","code":"101900710","trade":false,"enchantLevel":0},{"name":"후트킨의 마력포","level":44,"grade":"유일","type":"무기","subType":"마력포","code":"101900711","trade":false,"enchantLevel":0},{"name":"드빌카림의 마법포","level":52,"grade":"유일","type":"무기","subType":"마력포","code":"101900712","trade":false,"enchantLevel":0},{"name":"검은 폭풍의 마력포","level":55,"grade":"유일","type":"무기","subType":"마력포","code":"101900713","trade":false,"enchantLevel":0},{"name":"현상금 사냥꾼의 마력포","level":50,"grade":"유일","type":"무기","subType":"마력포","code":"101900716","trade":false,"enchantLevel":0},{"name":"전문 해결사의 마력포","level":50,"grade":"유일","type":"무기","subType":"마력포","code":"101900717","trade":false,"enchantLevel":0},{"name":"봉령의 마력포","level":35,"grade":"유일","type":"무기","subType":"마력포","code":"101900718","trade":false,"enchantLevel":0},{"name":"봉혼의 마력포","level":40,"grade":"유일","type":"무기","subType":"마력포","code":"101900719","trade":false,"enchantLevel":0},{"name":"봉신의 마력포","level":45,"grade":"유일","type":"무기","subType":"마력포","code":"101900720","trade":false,"enchantLevel":0},{"name":"헤라나스의 마력포","level":55,"grade":"유일","type":"무기","subType":"마력포","code":"101900721","trade":false,"enchantLevel":0},{"name":"테그라크의 마력포","level":55,"grade":"유일","type":"무기","subType":"마력포","code":"101900722","trade":false,"enchantLevel":0},{"name":"현상금 추적자의 마력포","level":55,"grade":"유일","type":"무기","subType":"마력포","code":"101900725","trade":false,"enchantLevel":0},{"name":"이름난 해결사의 마력포","level":55,"grade":"유일","type":"무기","subType":"마력포","code":"101900726","trade":false,"enchantLevel":0},{"name":"사려깊은 조언자의 마력포","level":45,"grade":"유일","type":"무기","subType":"마력포","code":"101900727","trade":false,"enchantLevel":0},{"name":"현명한 조언자의 마력포","level":45,"grade":"유일","type":"무기","subType":"마력포","code":"101900728","trade":false,"enchantLevel":0},{"name":"사려깊은 지도자의 마력포","level":55,"grade":"유일","type":"무기","subType":"마력포","code":"101900729","trade":false,"enchantLevel":0},{"name":"현명한 지도자의 마력포","level":55,"grade":"유일","type":"무기","subType":"마력포","code":"101900730","trade":false,"enchantLevel":0},{"name":"천군 지원병의 마력포","level":50,"grade":"유일","type":"무기","subType":"마력포","code":"101900731","trade":false,"enchantLevel":0},{"name":"마군 지원병의 마력포","level":50,"grade":"유일","type":"무기","subType":"마력포","code":"101900732","trade":false,"enchantLevel":0},{"name":"텔레마커스의 마력포","level":35,"grade":"유일","type":"무기","subType":"마력포","code":"101900735","trade":false,"enchantLevel":0},{"name":"아에기르의 마력포","level":35,"grade":"유일","type":"무기","subType":"마력포","code":"101900736","trade":false,"enchantLevel":0},{"name":"수라마의 마력포","level":55,"grade":"유일","type":"무기","subType":"마력포","code":"101900737","trade":false,"enchantLevel":0},{"name":"수라마의 마력포","level":55,"grade":"유일","type":"무기","subType":"마력포","code":"101900738","trade":false,"enchantLevel":0},{"name":"지룡포","level":55,"grade":"유일","type":"무기","subType":"마력포","code":"101900739","trade":false,"enchantLevel":0},{"name":"지룡포","level":55,"grade":"유일","type":"무기","subType":"마력포","code":"101900740","trade":false,"enchantLevel":0},{"name":"라크샤의 마력포","level":57,"grade":"유일","type":"무기","subType":"마력포","code":"101900741","trade":false,"enchantLevel":0},{"name":"에노아의 마력포","level":57,"grade":"유일","type":"무기","subType":"마력포","code":"101900742","trade":false,"enchantLevel":0},{"name":"알트요프의 마력포","level":57,"grade":"유일","type":"무기","subType":"마력포","code":"101900743","trade":false,"enchantLevel":0},{"name":"파괴신의 마력포","level":60,"grade":"유일","type":"무기","subType":"마력포","code":"101900762","trade":false,"enchantLevel":0},{"name":"가디언 친위대의 마력포","level":60,"grade":"유일","type":"무기","subType":"마력포","code":"101900765","trade":false,"enchantLevel":0},{"name":"가디언 친위대장의 마력포","level":60,"grade":"영웅","type":"무기","subType":"마력포","code":"101900766","trade":false,"enchantLevel":0},{"name":"아칸 친위대의 마력포","level":60,"grade":"유일","type":"무기","subType":"마력포","code":"101900769","trade":false,"enchantLevel":0},{"name":"아칸 친위대장의 마력포","level":60,"grade":"영웅","type":"무기","subType":"마력포","code":"101900770","trade":false,"enchantLevel":0},{"name":"아델라의 마력포","level":60,"grade":"유일","type":"무기","subType":"마력포","code":"101900776","trade":false,"enchantLevel":0},{"name":"시엘의 광휘 마력포","level":60,"grade":"유일","type":"무기","subType":"마력포","code":"101900777","trade":false,"enchantLevel":0},{"name":"아델라의 마력포","level":60,"grade":"유일","type":"무기","subType":"마력포","code":"101900783","trade":false,"enchantLevel":0},{"name":"시엘의 광휘 마력포","level":60,"grade":"유일","type":"무기","subType":"마력포","code":"101900784","trade":false,"enchantLevel":0},{"name":"티아마트 군단병의 마력포","level":59,"grade":"유일","type":"무기","subType":"마력포","code":"101900785","trade":false,"enchantLevel":0},{"name":"연족 정예병의 마력포","level":60,"grade":"유일","type":"무기","subType":"마력포","code":"101900788","trade":false,"enchantLevel":0},{"name":"카룬의 마력포","level":60,"grade":"영웅","type":"무기","subType":"마력포","code":"101900789","trade":false,"enchantLevel":0},{"name":"예민한 파드마샤의 마력포","level":55,"grade":"영웅","type":"무기","subType":"마력포","code":"101900790","trade":false,"enchantLevel":0},{"name":"하리두의 마력포","level":57,"grade":"유일","type":"무기","subType":"마력포","code":"101900792","trade":false,"enchantLevel":0},{"name":"드바림의 마력포","level":58,"grade":"유일","type":"무기","subType":"마력포","code":"101900795","trade":false,"enchantLevel":0},{"name":"타타르의 마력포","level":58,"grade":"유일","type":"무기","subType":"마력포","code":"101900796","trade":false,"enchantLevel":0},{"name":"수호군단 군단병의 마력포","level":60,"grade":"유일","type":"무기","subType":"마력포","code":"101900799","trade":false,"enchantLevel":0},{"name":"분노한 헤라나스의 주포","level":55,"grade":"영웅","type":"무기","subType":"마력포","code":"101900802","trade":false,"enchantLevel":0},{"name":"분노한 테그라크의 주포","level":55,"grade":"영웅","type":"무기","subType":"마력포","code":"101900803","trade":false,"enchantLevel":0},{"name":"정예 가디언 친위대의 마력포","level":60,"grade":"유일","type":"무기","subType":"마력포","code":"101900804","trade":false,"enchantLevel":0},{"name":"정예 가디언 친위대장의 마력포","level":60,"grade":"영웅","type":"무기","subType":"마력포","code":"101900805","trade":false,"enchantLevel":0},{"name":"정예 아칸 친위대의 마력포","level":60,"grade":"유일","type":"무기","subType":"마력포","code":"101900806","trade":false,"enchantLevel":0},{"name":"정예 아칸 친위대장의 마력포","level":60,"grade":"영웅","type":"무기","subType":"마력포","code":"101900807","trade":false,"enchantLevel":0},{"name":"루미나시엘 마력포","level":60,"grade":"영웅","type":"무기","subType":"마력포","code":"101900808","trade":false,"enchantLevel":0},{"name":"천족 데바니온 마력포","level":60,"grade":"영웅","type":"무기","subType":"마력포","code":"101900809","trade":false,"enchantLevel":0},{"name":"킬리오스의 마력포","level":56,"grade":"유일","type":"무기","subType":"마력포","code":"101900810","trade":false,"enchantLevel":0},{"name":"아이마의 마력포","level":56,"grade":"유일","type":"무기","subType":"마력포","code":"101900811","trade":false,"enchantLevel":0},{"name":"분노의 파편포","level":60,"grade":"영웅","type":"무기","subType":"마력포","code":"101900812","trade":false,"enchantLevel":0},{"name":"샤보르칸의 마력포","level":60,"grade":"유일","type":"무기","subType":"마력포","code":"101900814","trade":false,"enchantLevel":0},{"name":"쿰반다의 마력포","level":60,"grade":"유일","type":"무기","subType":"마력포","code":"101900815","trade":false,"enchantLevel":0},{"name":"수호군단의 마력포","level":60,"grade":"유일","type":"무기","subType":"마력포","code":"101900816","trade":false,"enchantLevel":0},{"name":"부서진 심연의 마력포","level":60,"grade":"유일","type":"무기","subType":"마력포","code":"101900817","trade":false,"enchantLevel":0},{"name":"템페르 수석교관의 신성한 마력포","level":55,"grade":"영웅","type":"무기","subType":"마력포","code":"101900818","trade":false,"enchantLevel":0},{"name":"템페르 교관의 신성한 마력포","level":55,"grade":"유일","type":"무기","subType":"마력포","code":"101900819","trade":false,"enchantLevel":0},{"name":"템페르 교관의 마력포","level":55,"grade":"유일","type":"무기","subType":"마력포","code":"101900820","trade":false,"enchantLevel":0},{"name":"템페르 수석교관의 신성한 마력포","level":55,"grade":"영웅","type":"무기","subType":"마력포","code":"101900822","trade":false,"enchantLevel":0},{"name":"템페르 교관의 신성한 마력포","level":55,"grade":"유일","type":"무기","subType":"마력포","code":"101900823","trade":false,"enchantLevel":0},{"name":"템페르 교관의 마력포","level":55,"grade":"유일","type":"무기","subType":"마력포","code":"101900824","trade":false,"enchantLevel":0},{"name":"템페르 수석교관의 고결한 마력포","level":55,"grade":"영웅","type":"무기","subType":"마력포","code":"101900826","trade":false,"enchantLevel":0},{"name":"템페르 교관의 신성한 마력포","level":55,"grade":"유일","type":"무기","subType":"마력포","code":"101900827","trade":false,"enchantLevel":0},{"name":"템페르 수석교관의 고결한 마력포","level":55,"grade":"영웅","type":"무기","subType":"마력포","code":"101900828","trade":false,"enchantLevel":0},{"name":"템페르 교관의 신성한 마력포","level":55,"grade":"유일","type":"무기","subType":"마력포","code":"101900829","trade":false,"enchantLevel":0},{"name":"템페르 수석교관의 고결한 마력포","level":55,"grade":"영웅","type":"무기","subType":"마력포","code":"101900832","trade":false,"enchantLevel":0},{"name":"템페르 수석교관의 고결한 마력포","level":55,"grade":"영웅","type":"무기","subType":"마력포","code":"101900833","trade":false,"enchantLevel":0},{"name":"템페르 투사의 신성한 마력포","level":55,"grade":"유일","type":"무기","subType":"마력포","code":"101900834","trade":false,"enchantLevel":0},{"name":"템페르 투사의 신성한 마력포","level":55,"grade":"유일","type":"무기","subType":"마력포","code":"101900835","trade":false,"enchantLevel":0},{"name":"템페르 승리자의 신성한 마력포","level":55,"grade":"영웅","type":"무기","subType":"마력포","code":"101900836","trade":false,"enchantLevel":0},{"name":"템페르 승리자의 신성한 마력포","level":55,"grade":"영웅","type":"무기","subType":"마력포","code":"101900837","trade":false,"enchantLevel":0},{"name":"템페르 승리자의 고결한 마력포","level":55,"grade":"영웅","type":"무기","subType":"마력포","code":"101900838","trade":false,"enchantLevel":0},{"name":"템페르 승리자의 고결한 마력포","level":55,"grade":"영웅","type":"무기","subType":"마력포","code":"101900839","trade":false,"enchantLevel":0},{"name":"마키아의 마력포","level":60,"grade":"영웅","type":"무기","subType":"마력포","code":"101900840","trade":false,"enchantLevel":0},{"name":"굴라레의 마력포","level":60,"grade":"영웅","type":"무기","subType":"마력포","code":"101900841","trade":false,"enchantLevel":0},{"name":"케사스의 마력포","level":60,"grade":"영웅","type":"무기","subType":"마력포","code":"101900842","trade":false,"enchantLevel":0},{"name":"빅토르의 마력포","level":60,"grade":"영웅","type":"무기","subType":"마력포","code":"101900843","trade":false,"enchantLevel":0},{"name":"주노스의 마력포","level":60,"grade":"유일","type":"무기","subType":"마력포","code":"101900844","trade":false,"enchantLevel":0},{"name":"시닌의 마력포","level":60,"grade":"유일","type":"무기","subType":"마력포","code":"101900845","trade":false,"enchantLevel":0},{"name":"천군 초년병의 마력포","level":25,"grade":"유일","type":"무기","subType":"마력포","code":"101900846","trade":false,"enchantLevel":0},{"name":"마군 초년병의 마력포","level":25,"grade":"유일","type":"무기","subType":"마력포","code":"101900847","trade":false,"enchantLevel":0},{"name":"용제의 용기","level":60,"grade":"신화","type":"무기","subType":"마력포","code":"101900848","trade":false,"enchantLevel":0},{"name":"가디언 친위대의 신성한 마력포","level":60,"grade":"유일","type":"무기","subType":"마력포","code":"101900849","trade":false,"enchantLevel":0},{"name":"가디언 친위대장의 신성한 마력포","level":60,"grade":"영웅","type":"무기","subType":"마력포","code":"101900850","trade":false,"enchantLevel":0},{"name":"아칸 친위대의 신성한 마력포","level":60,"grade":"유일","type":"무기","subType":"마력포","code":"101900851","trade":false,"enchantLevel":0},{"name":"아칸 친위대장의 신성한 마력포","level":60,"grade":"영웅","type":"무기","subType":"마력포","code":"101900852","trade":false,"enchantLevel":0},{"name":"바사르티의 마력포","level":60,"grade":"영웅","type":"무기","subType":"마력포","code":"101900853","trade":false,"enchantLevel":0},{"name":"수나야카의 마력포","level":60,"grade":"영웅","type":"무기","subType":"마력포","code":"101900854","trade":false,"enchantLevel":0},{"name":"타타르의 마력포","level":58,"grade":"영웅","type":"무기","subType":"마력포","code":"101900855","trade":false,"enchantLevel":0},{"name":"용제의 마력포","level":60,"grade":"영웅","type":"무기","subType":"마력포","code":"101900856","trade":false,"enchantLevel":0},{"name":"티아마트 친위대의 마력포","level":60,"grade":"영웅","type":"무기","subType":"마력포","code":"101900857","trade":false,"enchantLevel":0},{"name":"고대 정령의 마력포","level":60,"grade":"유일","type":"무기","subType":"마력포","code":"101900858","trade":false,"enchantLevel":0},{"name":"각인된 명인의 가르데니아 마력포","level":55,"grade":"영웅","type":"무기","subType":"마력포","code":"101900859","trade":false,"enchantLevel":0},{"name":"각인된 명인의 마키노 마력포","level":55,"grade":"영웅","type":"무기","subType":"마력포","code":"101900860","trade":false,"enchantLevel":0},{"name":"히샤디탄의 마력포","level":60,"grade":"영웅","type":"무기","subType":"마력포","code":"101900861","trade":false,"enchantLevel":0},{"name":"불의 마력포","level":60,"grade":"영웅","type":"무기","subType":"마력포","code":"101900862","trade":false,"enchantLevel":0},{"name":"NPC 일반 어비스 마력포","level":1,"grade":"유일","type":"무기","subType":"마력포","code":"101900863","trade":false,"enchantLevel":0},{"name":"NPC 총사 어비스 마력포","level":1,"grade":"유일","type":"무기","subType":"마력포","code":"101900864","trade":false,"enchantLevel":0},{"name":"NPC 마족 어비스 마력포","level":1,"grade":"유일","type":"무기","subType":"마력포","code":"101900865","trade":false,"enchantLevel":0},{"name":"NPC 주신의 하사품 전승 마력포","level":1,"grade":"유일","type":"무기","subType":"마력포","code":"101900866","trade":false,"enchantLevel":0},{"name":"NPC 강철 장미 마력포","level":1,"grade":"유일","type":"무기","subType":"마력포","code":"101900867","trade":false,"enchantLevel":0},{"name":"NPC 브리트라 마력포","level":1,"grade":"유일","type":"무기","subType":"마력포","code":"101900868","trade":false,"enchantLevel":0},{"name":"NPC 지하 필드 마력포","level":1,"grade":"유일","type":"무기","subType":"마력포","code":"101900869","trade":false,"enchantLevel":0},{"name":"NPC 고대 유물 마력포","level":1,"grade":"유일","type":"무기","subType":"마력포","code":"101900870","trade":false,"enchantLevel":0},{"name":"NPC 고대주화 마력포","level":1,"grade":"유일","type":"무기","subType":"마력포","code":"101900871","trade":false,"enchantLevel":0},{"name":"NPC 일반 제작 마력포","level":1,"grade":"유일","type":"무기","subType":"마력포","code":"101900872","trade":false,"enchantLevel":0},{"name":"NPC 주신의 하사품 영웅 마력포","level":1,"grade":"유일","type":"무기","subType":"마력포","code":"101900873","trade":false,"enchantLevel":0},{"name":"NPC 강철 장미 마력포 02a","level":1,"grade":"유일","type":"무기","subType":"마력포","code":"101900874","trade":false,"enchantLevel":0},{"name":"NPC PVP 추가 마력포 01a","level":1,"grade":"유일","type":"무기","subType":"마력포","code":"101900875","trade":false,"enchantLevel":0},{"name":"NPC 일반 제작 마력포 03a","level":1,"grade":"유일","type":"무기","subType":"마력포","code":"101900876","trade":false,"enchantLevel":0},{"name":"무형의 마력포(3일)","level":30,"grade":"유일","type":"무기","subType":"마력포","code":"101900877","trade":false,"enchantLevel":0},{"name":"무형의 마력포(7일)","level":40,"grade":"유일","type":"무기","subType":"마력포","code":"101900878","trade":false,"enchantLevel":0},{"name":"무형의 마력포(14일)","level":50,"grade":"유일","type":"무기","subType":"마력포","code":"101900879","trade":false,"enchantLevel":0},{"name":"무상의 마력포(3일)","level":30,"grade":"유일","type":"무기","subType":"마력포","code":"101900880","trade":false,"enchantLevel":0},{"name":"무념의 마력포(7일)","level":40,"grade":"유일","type":"무기","subType":"마력포","code":"101900881","trade":false,"enchantLevel":0},{"name":"무념의 마력포(14일)","level":50,"grade":"유일","type":"무기","subType":"마력포","code":"101900882","trade":false,"enchantLevel":0},{"name":"무상의 마력포(3일)","level":30,"grade":"유일","type":"무기","subType":"마력포","code":"101900883","trade":false,"enchantLevel":0},{"name":"무상의 마력포(7일)","level":40,"grade":"유일","type":"무기","subType":"마력포","code":"101900884","trade":false,"enchantLevel":0},{"name":"무상의 마력포(14일)","level":50,"grade":"유일","type":"무기","subType":"마력포","code":"101900885","trade":false,"enchantLevel":0},{"name":"몽환의 마력포(3일)","level":30,"grade":"유일","type":"무기","subType":"마력포","code":"101900886","trade":false,"enchantLevel":0},{"name":"몽환의 마력포(7일)","level":40,"grade":"유일","type":"무기","subType":"마력포","code":"101900887","trade":false,"enchantLevel":0},{"name":"몽환의 마력포(14일)","level":50,"grade":"유일","type":"무기","subType":"마력포","code":"101900888","trade":false,"enchantLevel":0},{"name":"몽중의 마력포(3일)","level":30,"grade":"유일","type":"무기","subType":"마력포","code":"101900889","trade":false,"enchantLevel":0},{"name":"몽중의 마력포(7일)","level":40,"grade":"유일","type":"무기","subType":"마력포","code":"101900890","trade":false,"enchantLevel":0},{"name":"몽상의 마력포(14일)","level":50,"grade":"유일","type":"무기","subType":"마력포","code":"101900891","trade":false,"enchantLevel":0},{"name":"몽상의 마력포(3일)","level":30,"grade":"유일","type":"무기","subType":"마력포","code":"101900892","trade":false,"enchantLevel":0},{"name":"몽상의 마력포(7일)","level":40,"grade":"유일","type":"무기","subType":"마력포","code":"101900893","trade":false,"enchantLevel":0},{"name":"몽상의 마력포(14일)","level":50,"grade":"유일","type":"무기","subType":"마력포","code":"101900894","trade":false,"enchantLevel":0},{"name":"격노한 야멘네스의 마력포","level":60,"grade":"영웅","type":"무기","subType":"마력포","code":"101900895","trade":false,"enchantLevel":0},{"name":"바실리스크 골각 마력포","level":60,"grade":"영웅","type":"무기","subType":"마력포","code":"101900900","trade":false,"enchantLevel":0},{"name":"핏빛 화염의 마력포","level":60,"grade":"영웅","type":"무기","subType":"마력포","code":"101900901","trade":false,"enchantLevel":0},{"name":"광혈의 마력포","level":60,"grade":"영웅","type":"무기","subType":"마력포","code":"101900902","trade":false,"enchantLevel":0},{"name":"염화의 마력포","level":60,"grade":"영웅","type":"무기","subType":"마력포","code":"101900903","trade":false,"enchantLevel":0},{"name":"용암의 마력포","level":60,"grade":"영웅","type":"무기","subType":"마력포","code":"101900904","trade":false,"enchantLevel":0},{"name":"빛나는 바실리스크 골각 마력포","level":60,"grade":"영웅","type":"무기","subType":"마력포","code":"101900905","trade":false,"enchantLevel":0},{"name":"빛나는 핏빛 화염의 마력포","level":60,"grade":"영웅","type":"무기","subType":"마력포","code":"101900906","trade":false,"enchantLevel":0},{"name":"빛나는 광혈의 마력포","level":60,"grade":"영웅","type":"무기","subType":"마력포","code":"101900907","trade":false,"enchantLevel":0},{"name":"빛나는 염화의 마력포","level":60,"grade":"영웅","type":"무기","subType":"마력포","code":"101900908","trade":false,"enchantLevel":0},{"name":"빛나는 용암의 마력포","level":60,"grade":"영웅","type":"무기","subType":"마력포","code":"101900909","trade":false,"enchantLevel":0},{"name":"NPC 커먼 마력포","level":1,"grade":"유일","type":"무기","subType":"마력포","code":"101900910","trade":false,"enchantLevel":0},{"name":"NPC 레어 마력포","level":1,"grade":"유일","type":"무기","subType":"마력포","code":"101900911","trade":false,"enchantLevel":0},{"name":"NPC 레전드 마력포","level":1,"grade":"유일","type":"무기","subType":"마력포","code":"101900912","trade":false,"enchantLevel":0},{"name":"NPC 유일 마력포","level":1,"grade":"유일","type":"무기","subType":"마력포","code":"101900913","trade":false,"enchantLevel":0},{"name":"NPC 에픽 마력포","level":1,"grade":"유일","type":"무기","subType":"마력포","code":"101900914","trade":false,"enchantLevel":0},{"name":"NPC 어비스 일반 마력포","level":1,"grade":"유일","type":"무기","subType":"마력포","code":"101900915","trade":false,"enchantLevel":0},{"name":"NPC 드라코닉 제작 마력포","level":1,"grade":"유일","type":"무기","subType":"마력포","code":"101900916","trade":false,"enchantLevel":0},{"name":"NPC 템페르 마력포","level":1,"grade":"유일","type":"무기","subType":"마력포","code":"101900917","trade":false,"enchantLevel":0},{"name":"NPC 템페르 pvp 마력포","level":1,"grade":"유일","type":"무기","subType":"마력포","code":"101900918","trade":false,"enchantLevel":0},{"name":"NPC 타하바타 마력포","level":1,"grade":"유일","type":"무기","subType":"마력포","code":"101900919","trade":false,"enchantLevel":0},{"name":"NPC 루드라 마력포","level":1,"grade":"유일","type":"무기","subType":"마력포","code":"101900920","trade":false,"enchantLevel":0},{"name":"NPC 티아마트 외변 마력포","level":1,"grade":"유일","type":"무기","subType":"마력포","code":"101900921","trade":false,"enchantLevel":0},{"name":"NPC 티아마트 신화 마력포","level":1,"grade":"유일","type":"무기","subType":"마력포","code":"101900922","trade":false,"enchantLevel":0},{"name":"NPC 티아마트 영웅 마력포","level":1,"grade":"유일","type":"무기","subType":"마력포","code":"101900923","trade":false,"enchantLevel":0},{"name":"NPC 티아마트 유일 마력포","level":1,"grade":"유일","type":"무기","subType":"마력포","code":"101900924","trade":false,"enchantLevel":0},{"name":"NPC 데바니온 마력포","level":1,"grade":"유일","type":"무기","subType":"마력포","code":"101900925","trade":false,"enchantLevel":0},{"name":"NPC 하우징 마력포","level":1,"grade":"유일","type":"무기","subType":"마력포","code":"101900926","trade":false,"enchantLevel":0},{"name":"NPC 레기온 마력포","level":1,"grade":"유일","type":"무기","subType":"마력포","code":"101900927","trade":false,"enchantLevel":0},{"name":"NPC 강철장미 슈라크 장총","level":1,"grade":"유일","type":"무기","subType":"마력포","code":"101900961","trade":false,"enchantLevel":0},{"name":"천군 5급 정예 군단병의 마력포","level":36,"grade":"유일","type":"무기","subType":"마력포","code":"101900986","trade":false,"enchantLevel":0},{"name":"천군 4급 정예 군단병의 마력포","level":41,"grade":"유일","type":"무기","subType":"마력포","code":"101900987","trade":false,"enchantLevel":0},{"name":"천군 3급 정예 군단병의 마력포","level":46,"grade":"유일","type":"무기","subType":"마력포","code":"101900988","trade":false,"enchantLevel":0},{"name":"마군 5급 정예 군단병의 마력포","level":36,"grade":"유일","type":"무기","subType":"마력포","code":"101900989","trade":false,"enchantLevel":0},{"name":"마군 4급 정예 군단병의 마력포","level":41,"grade":"유일","type":"무기","subType":"마력포","code":"101900990","trade":false,"enchantLevel":0},{"name":"마군 3급 정예 군단병의 마력포","level":46,"grade":"유일","type":"무기","subType":"마력포","code":"101900991","trade":false,"enchantLevel":0},{"name":"강화된 섬광의 마력포","level":55,"grade":"유일","type":"무기","subType":"마력포","code":"101901003","trade":false,"enchantLevel":0},{"name":"강화된 섬광의 마력포","level":55,"grade":"유일","type":"무기","subType":"마력포","code":"101901004","trade":false,"enchantLevel":0},{"name":"가디언 정복자의 마력포","level":54,"grade":"영웅","type":"무기","subType":"마력포","code":"101901005","trade":false,"enchantLevel":0},{"name":"아칸 정복자의 마력포","level":54,"grade":"영웅","type":"무기","subType":"마력포","code":"101901006","trade":false,"enchantLevel":0},{"name":"영예 가디언 정복자의 마력포","level":60,"grade":"영웅","type":"무기","subType":"마력포","code":"101901007","trade":false,"enchantLevel":0},{"name":"영예 아칸 정복자의 마력포","level":60,"grade":"영웅","type":"무기","subType":"마력포","code":"101901008","trade":false,"enchantLevel":0},{"name":"초심자의 정예 가디언 마력포","level":40,"grade":"유일","type":"무기","subType":"마력포","code":"101901009","trade":false,"enchantLevel":0},{"name":"초심자의 정예 아칸 마력포","level":40,"grade":"유일","type":"무기","subType":"마력포","code":"101901010","trade":false,"enchantLevel":0},{"name":"NPC_인트로영상_대포","level":1,"grade":"유일","type":"무기","subType":"마력포","code":"101901016","trade":false,"enchantLevel":0},{"name":"NPC 브리트라 화이트 대포","level":1,"grade":"유일","type":"무기","subType":"마력포","code":"101901022","trade":false,"enchantLevel":0},{"name":"[자쿠룽] 타타르의 마력포","level":58,"grade":"영웅","type":"무기","subType":"마력포","code":"101901031","trade":false,"enchantLevel":0},{"name":"NPC 4.5 일반 어비스 대포","level":1,"grade":"유일","type":"무기","subType":"마력포","code":"101901033","trade":false,"enchantLevel":0},{"name":"NPC 4.5 마족 어비스 대포","level":1,"grade":"유일","type":"무기","subType":"마력포","code":"101901034","trade":false,"enchantLevel":0},{"name":"NPC 4.5 디펜스 인던 대포","level":1,"grade":"유일","type":"무기","subType":"마력포","code":"101901035","trade":false,"enchantLevel":0},{"name":"NPC 철벽컷신용 마력포","level":1,"grade":"유일","type":"무기","subType":"마력포","code":"101901055","trade":false,"enchantLevel":0},{"name":"NPC 점령지 천족 마력포 사격성","level":1,"grade":"유일","type":"무기","subType":"마력포","code":"101901057","trade":false,"enchantLevel":0},{"name":"NPC 점령지 마족 마력포 사격성","level":1,"grade":"유일","type":"무기","subType":"마력포","code":"101901058","trade":false,"enchantLevel":0},{"name":"NPC 월드이벤트 마력포","level":1,"grade":"유일","type":"무기","subType":"마력포","code":"101901072","trade":false,"enchantLevel":0},{"name":"NPC 루나토리움 마력포","level":1,"grade":"유일","type":"무기","subType":"마력포","code":"101901073","trade":false,"enchantLevel":0},{"name":"하급 브리트라 보급품 마력포","level":40,"grade":"유일","type":"무기","subType":"마력포","code":"101901097","trade":false,"enchantLevel":0},{"name":"상급 브리트라 보급품 마력포","level":55,"grade":"영웅","type":"무기","subType":"마력포","code":"101901098","trade":false,"enchantLevel":0},{"name":"숙련된 북풍의 마력포","level":21,"grade":"유일","type":"무기","subType":"마력포","code":"101901107","trade":false,"enchantLevel":0},{"name":"숙련된 북풍의 마력포","level":21,"grade":"유일","type":"무기","subType":"마력포","code":"101901108","trade":false,"enchantLevel":0},{"name":"엘테넨 정예 군단병의 마력포","level":36,"grade":"유일","type":"무기","subType":"마력포","code":"101901132","trade":false,"enchantLevel":0},{"name":"모르헤임 정예 군단병의 마력포","level":36,"grade":"유일","type":"무기","subType":"마력포","code":"101901133","trade":false,"enchantLevel":0},{"name":"인테르디카 특수 수호병의 마력포","level":41,"grade":"유일","type":"무기","subType":"마력포","code":"101901134","trade":false,"enchantLevel":0},{"name":"벨루스란 특수 수호병의 마력포","level":41,"grade":"유일","type":"무기","subType":"마력포","code":"101901135","trade":false,"enchantLevel":0},{"name":"인테르디카 정예 군단병의 마력포","level":46,"grade":"유일","type":"무기","subType":"마력포","code":"101901136","trade":false,"enchantLevel":0},{"name":"벨루스란 정예 군단병의 마력포","level":46,"grade":"유일","type":"무기","subType":"마력포","code":"101901137","trade":false,"enchantLevel":0},{"name":"아트레이아 수호자의 마력포","level":51,"grade":"유일","type":"무기","subType":"마력포","code":"101901138","trade":false,"enchantLevel":0},{"name":"아트레이아 수호자의 마력포","level":51,"grade":"유일","type":"무기","subType":"마력포","code":"101901139","trade":false,"enchantLevel":0},{"name":"정예 파견대의 데바니온 마력포","level":56,"grade":"영웅","type":"무기","subType":"마력포","code":"101901158","trade":false,"enchantLevel":0},{"name":"파견대의 데바니온 마력포","level":46,"grade":"유일","type":"무기","subType":"마력포","code":"101901159","trade":false,"enchantLevel":0},{"name":"나스토의 마력포","level":60,"grade":"유일","type":"무기","subType":"마력포","code":"101901160","trade":false,"enchantLevel":0},{"name":"천군 1급 정예 군단병의 마력포","level":56,"grade":"유일","type":"무기","subType":"마력포","code":"101901168","trade":false,"enchantLevel":0},{"name":"마군 1급 정예 군단병의 마력포","level":56,"grade":"유일","type":"무기","subType":"마력포","code":"101901178","trade":false,"enchantLevel":0},{"name":"검은별 텔타링 회원의 마력포","level":40,"grade":"유일","type":"무기","subType":"마력포","code":"101901188","trade":false,"enchantLevel":0},{"name":"고결한 데바니온의 마력포","level":60,"grade":"영웅","type":"무기","subType":"마력포","code":"101901220","trade":false,"enchantLevel":0},{"name":"카룬의 마력포","level":60,"grade":"영웅","type":"무기","subType":"마력포","code":"101901221","trade":false,"enchantLevel":0},{"name":"NPC_5.1_어비스 천족 대포","level":1,"grade":"유일","type":"무기","subType":"마력포","code":"101901224","trade":false,"enchantLevel":0},{"name":"NPC_5.1_어비스 마족 대포","level":1,"grade":"유일","type":"무기","subType":"마력포","code":"101901225","trade":false,"enchantLevel":0},{"name":"트리로언의 마력포","level":50,"grade":"유일","type":"무기","subType":"마력포","code":"101901292","trade":false,"enchantLevel":0},{"name":"란마르크의 마력포","level":50,"grade":"유일","type":"무기","subType":"마력포","code":"101901293","trade":false,"enchantLevel":0},{"name":"제47 군단장의 마력포","level":50,"grade":"유일","type":"무기","subType":"마력포","code":"101901294","trade":false,"enchantLevel":0},{"name":"정예 원정대 데바 마력포","level":55,"grade":"영웅","type":"무기","subType":"마력포","code":"101901318","trade":false,"enchantLevel":0},{"name":"새싹 데바의 마력포","level":50,"grade":"유일","type":"무기","subType":"마력포","code":"101901381","trade":false,"enchantLevel":0},{"name":"빛나는 태양의 마력포","level":10,"grade":"궁극","type":"무기","subType":"마력포","code":"101950211","trade":false,"enchantLevel":0},{"name":"[각인] 빛나는 명월의 마력포","level":10,"grade":"궁극","type":"무기","subType":"마력포","code":"101950212","trade":false,"enchantLevel":0},{"name":"[각인] 빛나는 유성의 마력포","level":10,"grade":"궁극","type":"무기","subType":"마력포","code":"101950213","trade":false,"enchantLevel":0},{"name":"타오르는 태양의 마력포 - 태양의 기운","level":10,"grade":"궁극","type":"무기","subType":"마력포","code":"101950214","trade":false,"enchantLevel":0},{"name":"궁극의 참혹한 침입자 마력포 - 네자칸의 사도 (90일)","level":10,"grade":"궁극","type":"무기","subType":"마력포","code":"101950270","trade":false,"enchantLevel":0},{"name":"[각인] 얼어붙은 명월의 마력포 - 명월의 기운","level":10,"grade":"궁극","type":"무기","subType":"마력포","code":"101950273","trade":false,"enchantLevel":0},{"name":"[각인] 타오르는 태양의 마력포 - 태양의 기운","level":10,"grade":"궁극","type":"무기","subType":"마력포","code":"101950274","trade":false,"enchantLevel":0},{"name":"[각인] 찬란한 유성의 마력포 - 유성의 기운","level":10,"grade":"궁극","type":"무기","subType":"마력포","code":"101950295","trade":false,"enchantLevel":0}]